{
  "in_delr%om": {
    "summary": {
      "unit": "107",
      "headers": [
        "titldum",
        "header"
      ],
      "index_reads": [],
      "data_reads": [
        {
          "columns": [
            "dr_om_name(ii)",
            "dr(ii)"
          ],
          "rows": 1
        }
      ],
      "header_writes": [],
      "data_writes": []
    },
    "timeline": [
      {
        "kind": "open",
        "raw": "open (107,file=in_delr%om)",
        "line": 32
      },
      {
        "kind": "read",
        "raw": "read (107,*,iostat=eof) titldum",
        "line": 33
      },
      {
        "kind": "read",
        "raw": "read (107,*,iostat=eof) header",
        "line": 35
      },
      {
        "kind": "read",
        "raw": "read (107,*,iostat=eof) titldum",
        "line": 39
      },
      {
        "kind": "rewind",
        "raw": "rewind (107)",
        "line": 49
      },
      {
        "kind": "read",
        "raw": "read (107,*,iostat=eof) titldum",
        "line": 50
      },
      {
        "kind": "read",
        "raw": "read (107,*,iostat=eof) header",
        "line": 52
      },
      {
        "kind": "read",
        "raw": "read (107,*,iostat=eof) titldum",
        "line": 57
      },
      {
        "kind": "backspace",
        "raw": "backspace (107)",
        "line": 59
      },
      {
        "kind": "read",
        "raw": "read (107,*,iostat=eof) dr_om_name(ii), dr(ii)",
        "line": 60
      },
      {
        "kind": "close",
        "raw": "close (107)",
        "line": 63
      },
      {
        "kind": "close",
        "raw": "close(107)",
        "line": null
      }
    ]
  },
  "line_number": 1
}