{
  "gwflow.input": {
    "summary": {
      "unit": "in_gw",
      "headers": [
        "header",
        "grid_type",
        "cell_size",
        "ncell",
        "bc_type",
        "conn_type",
        "gw_soil_flag",
        "gw_satx_flag",
        "gw_pumpex_flag",
        "gw_tile_flag",
        "gw_res_flag",
        "gw_wet_flag",
        "gw_fp_flag",
        "gw_canal_flag",
        "gw_solute_flag",
        "gw_time_step",
        "out_cols",
        "nzones_aquK",
        "nzones_aquSy",
        "nzones_strK",
        "nzones_strbed",
        "gw_num_output",
        "gw_num_obs_wells",
        "gw_cell_obs_ss",
        "gw_bed_change"
      ],
      "index_reads": [],
      "data_reads": [
        {
          "columns": [
            "grid_nrow",
            "grid_ncol"
          ],
          "rows": 1
        },
        {
          "columns": [
            "gwflag_day",
            "gwflag_yr",
            "gwflag_aa"
          ],
          "rows": 1
        },
        {
          "columns": [
            "dum",
            "zones_aquK(i)"
          ],
          "rows": 1
        },
        {
          "columns": [
            "dum",
            "zones_aquSy(i)"
          ],
          "rows": 1
        },
        {
          "columns": [
            "dum",
            "zones_strK(i)"
          ],
          "rows": 1
        },
        {
          "columns": [
            "dum",
            "zones_strbed(i)"
          ],
          "rows": 1
        },
        {
          "columns": [
            "(grid_status(i,j),j=1,grid_ncol),i=1,grid_nrow"
          ],
          "rows": 1
        },
        {
          "columns": [
            "(grid_val(i,j),j=1,grid_ncol),i=1,grid_nrow"
          ],
          "rows": 5
        },
        {
          "columns": [
            "(grid_int(i,j),j=1,grid_ncol),i=1,grid_nrow"
          ],
          "rows": 2
        },
        {
          "columns": [
            "dum1",
            "gw_state(i)%stat",
            "gw_state(i)%elev",
            "gw_state(i)%thck",
            "K_zone",
            "Sy_zone",
            "delay(i)",
            "gw_state(i)%exdp",
            "gw_state(i)%init",
            "gw_state(i)%xcrd",
            "gw_state(i)%ycrd",
            "gw_state(i)%area",
            "gw_state(i)%ncon"
          ],
          "rows": 1
        },
        {
          "columns": [
            "dum1",
            "gw_state(i)%stat",
            "gw_state(i)%elev",
            "gw_state(i)%thck",
            "K_zone",
            "Sy_zone",
            "delay(i)",
            "gw_state(i)%exdp",
            "gw_state(i)%init",
            "gw_state(i)%xcrd",
            "gw_state(i)%ycrd",
            "gw_state(i)%area",
            "gw_state(i)%ncon",
            "cell_con(i)%cell_id(j),j=1,gw_state(i)%ncon"
          ],
          "rows": 1
        },
        {
          "columns": [
            "gw_output_yr(i)",
            "gw_output_day(i)"
          ],
          "rows": 1
        },
        {
          "columns": [
            "gw_obs_cells(k)",
            "usgs_id(k)"
          ],
          "rows": 1
        },
        {
          "columns": [
            "gw_obs_cells(k)"
          ],
          "rows": 1
        }
      ],
      "header_writes": [],
      "data_writes": []
    },
    "timeline": []
  },
  "gwflow.pumpex": {
    "summary": {
      "unit": "in_gw",
      "headers": [
        "header",
        "gw_npumpex"
      ],
      "index_reads": [],
      "data_reads": [
        {
          "columns": [
            "pumpex_cell",
            "gw_pumpex_nperiods(i)"
          ],
          "rows": 1
        },
        {
          "columns": [
            "gw_pumpex_dates(i,1,j)",
            "gw_pumpex_dates(i,2,j)",
            "gw_pumpex_rates(i,j)"
          ],
          "rows": 1
        }
      ],
      "header_writes": [],
      "data_writes": []
    },
    "timeline": []
  },
  "gwflow.tiles": {
    "summary": {
      "unit": "in_gw",
      "headers": [
        "header",
        "gw_tile_depth",
        "gw_tile_drain_area",
        "gw_tile_K",
        "gw_tile_group_flag",
        "gw_tile_num_group"
      ],
      "index_reads": [],
      "data_reads": [
        {
          "columns": [
            "num_tile_cells(i)"
          ],
          "rows": 1
        },
        {
          "columns": [
            "gw_tile_groups(i,j)"
          ],
          "rows": 1
        },
        {
          "columns": [
            "grid_int(i,j),j=1,grid_ncol"
          ],
          "rows": 1
        },
        {
          "columns": [
            "gw_state(i)%tile"
          ],
          "rows": 1
        }
      ],
      "header_writes": [],
      "data_writes": []
    },
    "timeline": []
  },
  "gwflow.solutes": {
    "summary": {
      "unit": "in_gw",
      "headers": [
        "header",
        "num_ts_transport",
        "gw_long_disp",
        "read_type",
        "single_value"
      ],
      "index_reads": [],
      "data_reads": [
        {
          "columns": [
            "name",
            "gwsol_sorb(s)",
            "gwsol_rctn(s)",
            "canal_out_conc(s)"
          ],
          "rows": 1
        },
        {
          "columns": [
            "grid_val(i,j),j=1,grid_ncol"
          ],
          "rows": 1
        },
        {
          "columns": [
            "gwsol_state(i)%solute(s)%conc,s=1,gw_nsolute"
          ],
          "rows": 1
        },
        {
          "columns": [
            "cell_int(i),i=1,ncell"
          ],
          "rows": 2
        },
        {
          "columns": [
            "grid_int(i,j),j=1,grid_ncol"
          ],
          "rows": 2
        }
      ],
      "header_writes": [],
      "data_writes": []
    },
    "timeline": []
  },
  "unit_*": {
    "summary": {
      "unit": "*",
      "headers": [],
      "index_reads": [],
      "data_reads": [],
      "header_writes": [],
      "data_writes": [
        {
          "columns": [
            "\"reading from groundwater file      \"",
            "date_time(5)",
            "date_time(6)",
            "date_time(7)"
          ],
          "rows": 1
        }
      ]
    },
    "timeline": [
      {
        "kind": "write",
        "raw": "write (*,111) \"reading from groundwater file      \", date_time(5), date_time(6), date_time(7)",
        "line": 148
      }
    ]
  },
  "unit_out_gw": {
    "summary": {
      "unit": "out_gw",
      "headers": [],
      "index_reads": [],
      "data_reads": [],
      "header_writes": [],
      "data_writes": [
        {
          "columns": [
            "'reading from file gwflow.input...'"
          ],
          "rows": 1
        },
        {
          "columns": [
            "'     reading basic information...'"
          ],
          "rows": 1
        },
        {
          "columns": [
            "'     checking for connection (HRU, LSU) files...'"
          ],
          "rows": 1
        },
        {
          "columns": [
            "'          found gwflow.hrucell: proceed'"
          ],
          "rows": 1
        },
        {
          "columns": [
            "'          gwflow.hrucell not found: using gwflow.lsucell'"
          ],
          "rows": 1
        },
        {
          "columns": [
            "'          gwflow.lsucell: gw-->soil transfer not simulated'"
          ],
          "rows": 2
        },
        {
          "columns": [
            "'          gwflow.lsucell: gw-->wetland transfer not simulated'"
          ],
          "rows": 2
        },
        {
          "columns": [
            "'          found gwflow.lsucell: proceed'"
          ],
          "rows": 1
        },
        {
          "columns": [
            "'          gwflow.lsucell not found: using gwflow.hrucell'"
          ],
          "rows": 1
        },
        {
          "columns": [
            "'          neither gwflow.hrucell or gwflow.lsucell found; stop simulation'"
          ],
          "rows": 1
        },
        {
          "columns": [
            "'     reading aquifer and streambed parameters...'"
          ],
          "rows": 1
        },
        {
          "columns": [
            "'          reading aquifer hydraulic conductivity'"
          ],
          "rows": 1
        },
        {
          "columns": [
            "'          reading aquifer specific yield'"
          ],
          "rows": 1
        },
        {
          "columns": [
            "'          reading streambed hydraulic conductivity'"
          ],
          "rows": 1
        },
        {
          "columns": [
            "'          reading streambed thickness'"
          ],
          "rows": 1
        },
        {
          "columns": [
            "'     reading grid cell information...'"
          ],
          "rows": 1
        },
        {
          "columns": [
            "'     counting number of active cells'"
          ],
          "rows": 1
        },
        {
          "columns": [
            "'     reading groundwater output times'"
          ],
          "rows": 1
        },
        {
          "columns": [
            "'     reading observation cells'"
          ],
          "rows": 1
        },
        {
          "columns": [
            "'additional gwflow preparation...'"
          ],
          "rows": 1
        },
        {
          "columns": [
            "'     processing channel-cell information'"
          ],
          "rows": 1
        },
        {
          "columns": [
            "'     allocate and prepare source-sink arrays...'"
          ],
          "rows": 1
        },
        {
          "columns": [
            "'          recharge from soil'"
          ],
          "rows": 1
        },
        {
          "columns": [
            "'          groundwater ET'"
          ],
          "rows": 1
        },
        {
          "columns": [
            "'          groundwater-channel exchange'"
          ],
          "rows": 1
        },
        {
          "columns": [
            "'          groundwater-->soil transfer'"
          ],
          "rows": 1
        },
        {
          "columns": [
            "'          groundwater saturation excess flow'"
          ],
          "rows": 1
        },
        {
          "columns": [
            "'          groundwater pumping for irrigation'"
          ],
          "rows": 1
        },
        {
          "columns": [
            "'          groundwater pumping external (gwflow.pumpex found)'"
          ],
          "rows": 1
        },
        {
          "columns": [
            "'          gwflow.pumpex not found; pumping not simulated'"
          ],
          "rows": 1
        },
        {
          "columns": [
            "'          groundwater-tile drainage outflow (gwflow.tiles found)'"
          ],
          "rows": 1
        },
        {
          "columns": [
            "'          gwflow.tiles not found; tile drainage not simulated'"
          ],
          "rows": 1
        },
        {
          "columns": [
            "'          groundwater-reservoir exchange (gwflow.rescells found)'"
          ],
          "rows": 1
        },
        {
          "columns": [
            "'          gwflow.rescells not found (groundwater-res exchange not simulated)'"
          ],
          "rows": 1
        },
        {
          "columns": [
            "'          groundwater-->wetland exchange'"
          ],
          "rows": 1
        },
        {
          "columns": [
            "'          groundwater-floodplain exchange (gwflow.floodplain found)'"
          ],
          "rows": 1
        },
        {
          "columns": [
            "'          gwflow.floodplain not found (groundwater-fp exchange not simulated)'"
          ],
          "rows": 1
        },
        {
          "columns": [
            "'          canal-->groundwater seepage (gwflow.canals found)'"
          ],
          "rows": 1
        },
        {
          "columns": [
            "'          gwflow.canals not found (canal seepage not simulated)'"
          ],
          "rows": 1
        },
        {
          "columns": [
            "'     groundwater solute transport preparation...'"
          ],
          "rows": 1
        },
        {
          "columns": [
            "'          groundwater solute being simulated (gwflow.solutes found)'"
          ],
          "rows": 1
        },
        {
          "columns": [
            "'     read and prepare connection (HRU-cell or LSU-cell)'"
          ],
          "rows": 1
        },
        {
          "columns": [
            "'          LSU-cell connections (gwflow.lsucell)'"
          ],
          "rows": 1
        },
        {
          "columns": [
            "'          HRU-cell connections (gwflow.hrucell)'"
          ],
          "rows": 1
        },
        {
          "columns": [
            "'          HRU-cell connections (gwflow.cellhru)'"
          ],
          "rows": 1
        },
        {
          "columns": [
            "'     initialize groundwater balance files and arrays'"
          ],
          "rows": 1
        },
        {
          "columns": [
            "'     final preparations...'"
          ],
          "rows": 1
        },
        {
          "columns": [
            "'          map recharge delay to HRUs'"
          ],
          "rows": 1
        },
        {
          "columns": [
            "'          prepare output files for monthly and annual average groundwater head'"
          ],
          "rows": 1
        },
        {
          "columns": [
            "'          prepare output files for monthly and annual average solute conc.'"
          ],
          "rows": 1
        },
        {
          "columns": [
            "'record of daily gwflow use...'"
          ],
          "rows": 1
        }
      ]
    },
    "timeline": [
      {
        "kind": "write",
        "raw": "write(out_gw,*)",
        "line": 151
      },
      {
        "kind": "write",
        "raw": "write(out_gw,*) 'reading from file gwflow.input...'",
        "line": 152
      },
      {
        "kind": "write",
        "raw": "write(out_gw,*) '     reading basic information...'",
        "line": 177
      },
      {
        "kind": "write",
        "raw": "write(out_gw,*) '     checking for connection (HRU, LSU) files...'",
        "line": 202
      },
      {
        "kind": "write",
        "raw": "write(out_gw,*) '          found gwflow.hrucell: proceed'",
        "line": 208
      },
      {
        "kind": "write",
        "raw": "write(out_gw,*) '          gwflow.hrucell not found: using gwflow.lsucell'",
        "line": 216
      },
      {
        "kind": "write",
        "raw": "write(out_gw,*) '          gwflow.lsucell: gw-->soil transfer not simulated'",
        "line": 217
      },
      {
        "kind": "write",
        "raw": "write(out_gw,*) '          gwflow.lsucell: gw-->wetland transfer not simulated'",
        "line": 218
      },
      {
        "kind": "write",
        "raw": "write(out_gw,*) '          found gwflow.lsucell: proceed'",
        "line": 228
      },
      {
        "kind": "write",
        "raw": "write(out_gw,*) '          gwflow.lsucell: gw-->soil transfer not simulated'",
        "line": 229
      },
      {
        "kind": "write",
        "raw": "write(out_gw,*) '          gwflow.lsucell: gw-->wetland transfer not simulated'",
        "line": 230
      },
      {
        "kind": "write",
        "raw": "write(out_gw,*) '          gwflow.lsucell not found: using gwflow.hrucell'",
        "line": 236
      },
      {
        "kind": "write",
        "raw": "write(out_gw,*) '          neither gwflow.hrucell or gwflow.lsucell found; stop simulation'",
        "line": 240
      },
      {
        "kind": "write",
        "raw": "write(out_gw,*) '     reading aquifer and streambed parameters...'",
        "line": 246
      },
      {
        "kind": "write",
        "raw": "write(out_gw,*) '          reading aquifer hydraulic conductivity'",
        "line": 249
      },
      {
        "kind": "write",
        "raw": "write(out_gw,*) '          reading aquifer specific yield'",
        "line": 259
      },
      {
        "kind": "write",
        "raw": "write(out_gw,*) '          reading streambed hydraulic conductivity'",
        "line": 268
      },
      {
        "kind": "write",
        "raw": "write(out_gw,*) '          reading streambed thickness'",
        "line": 277
      },
      {
        "kind": "write",
        "raw": "write(out_gw,*) '     reading grid cell information...'",
        "line": 288
      },
      {
        "kind": "write",
        "raw": "write(out_gw,*) '     counting number of active cells'",
        "line": 585
      },
      {
        "kind": "write",
        "raw": "write(out_gw,*) '     reading groundwater output times'",
        "line": 626
      },
      {
        "kind": "write",
        "raw": "write(out_gw,*) '     reading observation cells'",
        "line": 637
      },
      {
        "kind": "write",
        "raw": "write(out_gw,*)",
        "line": 718
      },
      {
        "kind": "write",
        "raw": "write(out_gw,*) 'additional gwflow preparation...'",
        "line": 719
      },
      {
        "kind": "write",
        "raw": "write(out_gw,*)",
        "line": 720
      },
      {
        "kind": "write",
        "raw": "write(out_gw,*) '     processing channel-cell information'",
        "line": 721
      },
      {
        "kind": "write",
        "raw": "write(out_gw,*) '     allocate and prepare source-sink arrays...'",
        "line": 740
      },
      {
        "kind": "write",
        "raw": "write(out_gw,*) '          recharge from soil'",
        "line": 786
      },
      {
        "kind": "write",
        "raw": "write(out_gw,*) '          groundwater ET'",
        "line": 794
      },
      {
        "kind": "write",
        "raw": "write(out_gw,*) '          groundwater-channel exchange'",
        "line": 812
      },
      {
        "kind": "write",
        "raw": "write(out_gw,*) '          groundwater-->soil transfer'",
        "line": 844
      },
      {
        "kind": "write",
        "raw": "write(out_gw,*) '          groundwater saturation excess flow'",
        "line": 877
      },
      {
        "kind": "write",
        "raw": "write(out_gw,*) '          groundwater pumping for irrigation'",
        "line": 906
      },
      {
        "kind": "write",
        "raw": "write(out_gw,*) '          groundwater pumping external (gwflow.pumpex found)'",
        "line": 951
      },
      {
        "kind": "write",
        "raw": "write(out_gw,*) '          gwflow.pumpex not found; pumping not simulated'",
        "line": 980
      },
      {
        "kind": "write",
        "raw": "write(out_gw,*) '          groundwater-tile drainage outflow (gwflow.tiles found)'",
        "line": 989
      },
      {
        "kind": "write",
        "raw": "write(out_gw,*) '          gwflow.tiles not found; tile drainage not simulated'",
        "line": 1055
      },
      {
        "kind": "write",
        "raw": "write(out_gw,*) '          groundwater-reservoir exchange (gwflow.rescells found)'",
        "line": 1063
      },
      {
        "kind": "write",
        "raw": "write(out_gw,*) '          gwflow.rescells not found (groundwater-res exchange not simulated)'",
        "line": 1113
      },
      {
        "kind": "write",
        "raw": "write(out_gw,*) '          groundwater-->wetland exchange'",
        "line": 1119
      },
      {
        "kind": "write",
        "raw": "write(out_gw,*) '          groundwater-floodplain exchange (gwflow.floodplain found)'",
        "line": 1134
      },
      {
        "kind": "write",
        "raw": "write(out_gw,*) '          gwflow.floodplain not found (groundwater-fp exchange not simulated)'",
        "line": 1185
      },
      {
        "kind": "write",
        "raw": "write(out_gw,*) '          canal-->groundwater seepage (gwflow.canals found)'",
        "line": 1194
      },
      {
        "kind": "write",
        "raw": "write(out_gw,*) '          gwflow.canals not found (canal seepage not simulated)'",
        "line": 1344
      },
      {
        "kind": "write",
        "raw": "write(out_gw,*)",
        "line": 1351
      },
      {
        "kind": "write",
        "raw": "write(out_gw,*) '     groundwater solute transport preparation...'",
        "line": 1393
      },
      {
        "kind": "write",
        "raw": "write(out_gw,*) '          groundwater solute being simulated (gwflow.solutes found)'",
        "line": 1394
      },
      {
        "kind": "write",
        "raw": "write(out_gw,*)",
        "line": 1670
      },
      {
        "kind": "write",
        "raw": "write(out_gw,*) '     read and prepare connection (HRU-cell or LSU-cell)'",
        "line": 1671
      },
      {
        "kind": "write",
        "raw": "write(out_gw,*) '          LSU-cell connections (gwflow.lsucell)'",
        "line": 1673
      },
      {
        "kind": "write",
        "raw": "write(out_gw,*) '          HRU-cell connections (gwflow.hrucell)'",
        "line": 1754
      },
      {
        "kind": "write",
        "raw": "write(out_gw,*) '          HRU-cell connections (gwflow.cellhru)'",
        "line": 1862
      },
      {
        "kind": "write",
        "raw": "write(out_gw,*)",
        "line": 1905
      },
      {
        "kind": "write",
        "raw": "write(out_gw,*) '     initialize groundwater balance files and arrays'",
        "line": 1906
      },
      {
        "kind": "write",
        "raw": "write(out_gw,*)",
        "line": 2278
      },
      {
        "kind": "write",
        "raw": "write(out_gw,*) '     final preparations...'",
        "line": 2279
      },
      {
        "kind": "write",
        "raw": "write(out_gw,*) '          map recharge delay to HRUs'",
        "line": 2280
      },
      {
        "kind": "write",
        "raw": "write(out_gw,*) '          prepare output files for monthly and annual average groundwater head'",
        "line": 2364
      },
      {
        "kind": "write",
        "raw": "write(out_gw,*) '          prepare output files for monthly and annual average solute conc.'",
        "line": 2374
      },
      {
        "kind": "write",
        "raw": "write(out_gw,*)",
        "line": 2436
      },
      {
        "kind": "write",
        "raw": "write(out_gw,*)",
        "line": 2437
      },
      {
        "kind": "write",
        "raw": "write(out_gw,*) 'record of daily gwflow use...'",
        "line": 2438
      },
      {
        "kind": "write",
        "raw": "write(out_gw,*)",
        "line": 2439
      }
    ]
  },
  "gwflow_state_obs_head": {
    "summary": {
      "unit": "out_gwobs",
      "headers": [],
      "index_reads": [],
      "data_reads": [],
      "header_writes": [],
      "data_writes": [
        {
          "columns": [
            "'Daily head (m) values for observation wells'"
          ],
          "rows": 1
        },
        {
          "columns": [
            "'cell:'",
            "gw_obs_cells(k),k=1,gw_num_obs_wells"
          ],
          "rows": 1
        }
      ]
    },
    "timeline": []
  },
  "usgs_annual_head": {
    "summary": {
      "unit": "in_usgs_head",
      "headers": [],
      "index_reads": [],
      "data_reads": [
        {
          "columns": [
            "usgs_site_id",
            "usgs_lat",
            "usgs_long",
            "head_vals(j),j=1,101"
          ],
          "rows": 1
        }
      ],
      "header_writes": [],
      "data_writes": []
    },
    "timeline": []
  },
  "gwflow_state_obs_head_usgs": {
    "summary": {
      "unit": "out_gwobs_usgs",
      "headers": [],
      "index_reads": [],
      "data_reads": [],
      "header_writes": [],
      "data_writes": [
        {
          "columns": [
            "'Average annual heads: USGS observed vs. simulated'"
          ],
          "rows": 1
        }
      ]
    },
    "timeline": []
  },
  "gwflow_flux_rech": {
    "summary": {
      "unit": "out_gw_rech",
      "headers": [],
      "index_reads": [],
      "data_reads": [],
      "header_writes": [],
      "data_writes": [
        {
          "columns": [
            "'Annual recharge flow (m3/day)'"
          ],
          "rows": 1
        }
      ]
    },
    "timeline": []
  },
  "gwflow_flux_gwet": {
    "summary": {
      "unit": "out_gw_et",
      "headers": [],
      "index_reads": [],
      "data_reads": [],
      "header_writes": [],
      "data_writes": [
        {
          "columns": [
            "'Annual groundwater ET rates (m3/day)'"
          ],
          "rows": 1
        }
      ]
    },
    "timeline": []
  },
  "gwflow_flux_gwsw": {
    "summary": {
      "unit": "out_gwsw",
      "headers": [],
      "index_reads": [],
      "data_reads": [],
      "header_writes": [],
      "data_writes": [
        {
          "columns": [
            "'Annual GW-SW Exchange flows (m3/day)'"
          ],
          "rows": 1
        }
      ]
    },
    "timeline": []
  },
  "gwflow_flux_soil": {
    "summary": {
      "unit": "out_gw_soil",
      "headers": [],
      "index_reads": [],
      "data_reads": [],
      "header_writes": [],
      "data_writes": [
        {
          "columns": [
            "'Annual groundwater-->soil transfers (m3/day)'"
          ],
          "rows": 1
        }
      ]
    },
    "timeline": []
  },
  "gwflow_flux_satx": {
    "summary": {
      "unit": "out_gw_satex",
      "headers": [],
      "index_reads": [],
      "data_reads": [],
      "header_writes": [],
      "data_writes": [
        {
          "columns": [
            "'Annual saturation excess flows (m3/day)'"
          ],
          "rows": 1
        }
      ]
    },
    "timeline": []
  },
  "gwflow_flux_ppag": {
    "summary": {
      "unit": "out_gw_pumpag",
      "headers": [],
      "index_reads": [],
      "data_reads": [],
      "header_writes": [],
      "data_writes": [
        {
          "columns": [
            "'Annual pumping rate (m3/day) (irrigation)'"
          ],
          "rows": 1
        }
      ]
    },
    "timeline": []
  },
  "gwflow_flux_pumping_deficient": {
    "summary": {
      "unit": "out_gw_pumpdef",
      "headers": [],
      "index_reads": [],
      "data_reads": [],
      "header_writes": [],
      "data_writes": [
        {
          "columns": [
            "'Annual rate (m3/day) not satisfied (irrigation)'"
          ],
          "rows": 1
        }
      ]
    },
    "timeline": []
  },
  "gwflow_flux_pumping_hru_yr": {
    "summary": {
      "unit": "out_hru_pump_yr",
      "headers": [],
      "index_reads": [],
      "data_reads": [],
      "header_writes": [],
      "data_writes": [
        {
          "columns": [
            "'Annual pumped volume (m3) (irrigation) for HRUs'"
          ],
          "rows": 1
        },
        {
          "columns": [
            "'Columns: each year of the simulation'"
          ],
          "rows": 1
        }
      ]
    },
    "timeline": []
  },
  "gwflow_flux_pumping_hru_mo": {
    "summary": {
      "unit": "out_hru_pump_mo",
      "headers": [],
      "index_reads": [],
      "data_reads": [],
      "header_writes": [],
      "data_writes": [
        {
          "columns": [
            "'Monthly pumped volume (m3) (irrigation) for HRUs'"
          ],
          "rows": 1
        },
        {
          "columns": [
            "'Columns: each month of the simulation'"
          ],
          "rows": 1
        }
      ]
    },
    "timeline": []
  },
  "gwflow.hru_pump_observe": {
    "summary": {
      "unit": "in_hru_pump_obs",
      "headers": [
        "num_hru_pump_obs"
      ],
      "index_reads": [],
      "data_reads": [
        {
          "columns": [
            "hru_pump_ids(i)"
          ],
          "rows": 1
        }
      ],
      "header_writes": [],
      "data_writes": []
    },
    "timeline": []
  },
  "gwflow_flux_pumping_hru_obs": {
    "summary": {
      "unit": "out_hru_pump_obs",
      "headers": [],
      "index_reads": [],
      "data_reads": [],
      "header_writes": [],
      "data_writes": [
        {
          "columns": [
            "'Daily groundwater pumping (m3) for specified HRUs'"
          ],
          "rows": 1
        },
        {
          "columns": [
            "'Columns = HRUs (same order as in gwflow.hru_pump_observe)'"
          ],
          "rows": 1
        },
        {
          "columns": [
            "'Time(day)    Daily pumping (m3)'"
          ],
          "rows": 1
        }
      ]
    },
    "timeline": []
  },
  "gwflow_flux_ppex": {
    "summary": {
      "unit": "out_gw_pumpex",
      "headers": [],
      "index_reads": [],
      "data_reads": [],
      "header_writes": [],
      "data_writes": [
        {
          "columns": [
            "'Annual pumping rate (m3/day) (specified)'"
          ],
          "rows": 1
        }
      ]
    },
    "timeline": []
  },
  "gwflow_tile_cell_groups": {
    "summary": {
      "unit": "out_tile_cells",
      "headers": [],
      "index_reads": [],
      "data_reads": [],
      "header_writes": [],
      "data_writes": [
        {
          "columns": [
            "'Total tile flow (m3/sec)'"
          ],
          "rows": 1
        }
      ]
    },
    "timeline": []
  },
  "gwflow_flux_tile": {
    "summary": {
      "unit": "out_gw_tile",
      "headers": [],
      "index_reads": [],
      "data_reads": [],
      "header_writes": [],
      "data_writes": [
        {
          "columns": [
            "'Annual tile flows (m3/day)'"
          ],
          "rows": 1
        }
      ]
    },
    "timeline": []
  },
  "gwflow.rescells": {
    "summary": {
      "unit": "in_res_cell",
      "headers": [
        "header",
        "res_thick",
        "res_K",
        "num_res_cells"
      ],
      "index_reads": [],
      "data_reads": [
        {
          "columns": [
            "res_cell",
            "res_id",
            "res_stage"
          ],
          "rows": 2
        }
      ],
      "header_writes": [],
      "data_writes": []
    },
    "timeline": []
  },
  "gwflow_flux_resv": {
    "summary": {
      "unit": "out_gw_res",
      "headers": [],
      "index_reads": [],
      "data_reads": [],
      "header_writes": [],
      "data_writes": [
        {
          "columns": [
            "'Annual groundwater-reservoir exchange (m3/day)'"
          ],
          "rows": 1
        }
      ]
    },
    "timeline": []
  },
  "gwflow_flux_wetland": {
    "summary": {
      "unit": "out_gw_wet",
      "headers": [],
      "index_reads": [],
      "data_reads": [],
      "header_writes": [],
      "data_writes": [
        {
          "columns": [
            "'Annual groundwater outflow to wetlands (m3/day)'"
          ],
          "rows": 1
        }
      ]
    },
    "timeline": []
  },
  "gwflow.floodplain": {
    "summary": {
      "unit": "in_fp_cell",
      "headers": [
        "header",
        "gw_fp_ncells"
      ],
      "index_reads": [],
      "data_reads": [
        {
          "columns": [
            "gw_fp_cellid(i)",
            "gw_fp_chanid(i)",
            "gw_fp_K(i)",
            "gw_fp_area(i)"
          ],
          "rows": 1
        }
      ],
      "header_writes": [],
      "data_writes": []
    },
    "timeline": []
  },
  "gwflow_flux_floodplain": {
    "summary": {
      "unit": "out_gw_fp",
      "headers": [],
      "index_reads": [],
      "data_reads": [],
      "header_writes": [],
      "data_writes": [
        {
          "columns": [
            "'Annual floodplain seepage (m3/day)'"
          ],
          "rows": 1
        }
      ]
    },
    "timeline": []
  },
  "gwflow.canals": {
    "summary": {
      "unit": "in_canal_cell",
      "headers": [
        "header",
        "gw_ncanal",
        "num_canalK_zones",
        "gw_canal_ncells"
      ],
      "index_reads": [],
      "data_reads": [
        {
          "columns": [
            "canal",
            "channel",
            "width",
            "depth",
            "thick",
            "day_beg",
            "day_end"
          ],
          "rows": 2
        },
        {
          "columns": [
            "dum1",
            "canalK_zones(i)"
          ],
          "rows": 1
        },
        {
          "columns": [
            "cell_num",
            "canal"
          ],
          "rows": 1
        },
        {
          "columns": [
            "cell_num",
            "canal",
            "length",
            "stage",
            "K_zone"
          ],
          "rows": 2
        }
      ],
      "header_writes": [],
      "data_writes": []
    },
    "timeline": []
  },
  "gwflow_flux_canl": {
    "summary": {
      "unit": "out_gw_canal",
      "headers": [],
      "index_reads": [],
      "data_reads": [],
      "header_writes": [],
      "data_writes": [
        {
          "columns": [
            "'Annual canal seepage (m3/day)'"
          ],
          "rows": 1
        }
      ]
    },
    "timeline": []
  },
  "gwflow.solutes.minerals": {
    "summary": {
      "unit": "in_gw_minl",
      "headers": [
        "header",
        "gw_nminl",
        "read_type",
        "single_value"
      ],
      "index_reads": [],
      "data_reads": [
        {
          "columns": [
            "grid_val(i,j),j=1,grid_ncol"
          ],
          "rows": 1
        },
        {
          "columns": [
            "gwsol_minl_state(i)%fract(m),m=1,gw_nminl"
          ],
          "rows": 1
        }
      ],
      "header_writes": [],
      "data_writes": []
    },
    "timeline": []
  },
  "gwflow_mass_rech": {
    "summary": {
      "unit": "out_sol_rech",
      "headers": [],
      "index_reads": [],
      "data_reads": [],
      "header_writes": [],
      "data_writes": [
        {
          "columns": [
            "'Annual recharge mass (kg/day)'"
          ],
          "rows": 1
        }
      ]
    },
    "timeline": []
  },
  "gwflow_mass_gwsw": {
    "summary": {
      "unit": "out_sol_gwsw",
      "headers": [],
      "index_reads": [],
      "data_reads": [],
      "header_writes": [],
      "data_writes": [
        {
          "columns": [
            "'Annual gw-channel exchange mass (kg/day)'"
          ],
          "rows": 1
        }
      ]
    },
    "timeline": []
  },
  "gwflow_mass_soil": {
    "summary": {
      "unit": "out_sol_soil",
      "headers": [],
      "index_reads": [],
      "data_reads": [],
      "header_writes": [],
      "data_writes": [
        {
          "columns": [
            "'Annual groundwater-->soil mass transfer (kg/day)'"
          ],
          "rows": 1
        }
      ]
    },
    "timeline": []
  },
  "gwflow_mass_satx": {
    "summary": {
      "unit": "out_sol_satx",
      "headers": [],
      "index_reads": [],
      "data_reads": [],
      "header_writes": [],
      "data_writes": [
        {
          "columns": [
            "'Annual saturation excess flow mass (kg/day)'"
          ],
          "rows": 1
        }
      ]
    },
    "timeline": []
  },
  "gwflow_mass_ppag": {
    "summary": {
      "unit": "out_sol_ppag",
      "headers": [],
      "index_reads": [],
      "data_reads": [],
      "header_writes": [],
      "data_writes": [
        {
          "columns": [
            "'Annual mass in pumping (kg/day) (irrigation)'"
          ],
          "rows": 1
        }
      ]
    },
    "timeline": []
  },
  "gwflow_mass_ppex": {
    "summary": {
      "unit": "out_sol_ppex",
      "headers": [],
      "index_reads": [],
      "data_reads": [],
      "header_writes": [],
      "data_writes": [
        {
          "columns": [
            "'Annual mass in pumping (kg/day) (specified)'"
          ],
          "rows": 1
        }
      ]
    },
    "timeline": []
  },
  "gwflow_mass_tile": {
    "summary": {
      "unit": "out_sol_tile",
      "headers": [],
      "index_reads": [],
      "data_reads": [],
      "header_writes": [],
      "data_writes": [
        {
          "columns": [
            "'Annual mass in tile flow (kg/day)'"
          ],
          "rows": 1
        }
      ]
    },
    "timeline": []
  },
  "gwflow_mass_resv": {
    "summary": {
      "unit": "out_sol_resv",
      "headers": [],
      "index_reads": [],
      "data_reads": [],
      "header_writes": [],
      "data_writes": [
        {
          "columns": [
            "'Annual groundwater-reservoir exchange mass (kg/day)'"
          ],
          "rows": 1
        }
      ]
    },
    "timeline": []
  },
  "gwflow_mass_wetl": {
    "summary": {
      "unit": "out_sol_wetl",
      "headers": [],
      "index_reads": [],
      "data_reads": [],
      "header_writes": [],
      "data_writes": [
        {
          "columns": [
            "'Annual groundwater-wetland exchange mass (kg/day)'"
          ],
          "rows": 1
        }
      ]
    },
    "timeline": []
  },
  "gwflow_mass_fpln": {
    "summary": {
      "unit": "out_sol_fpln",
      "headers": [],
      "index_reads": [],
      "data_reads": [],
      "header_writes": [],
      "data_writes": [
        {
          "columns": [
            "'Annual floodplain seepage mass (kg/day)'"
          ],
          "rows": 1
        }
      ]
    },
    "timeline": []
  },
  "gwflow_mass_canl": {
    "summary": {
      "unit": "out_sol_canl",
      "headers": [],
      "index_reads": [],
      "data_reads": [],
      "header_writes": [],
      "data_writes": [
        {
          "columns": [
            "'Annual canal seepage mass (kg/day)'"
          ],
          "rows": 1
        }
      ]
    },
    "timeline": []
  },
  "gwflow_flux_reaction": {
    "summary": {
      "unit": "out_gw_chem",
      "headers": [],
      "index_reads": [],
      "data_reads": [],
      "header_writes": [],
      "data_writes": [
        {
          "columns": [
            "'Annual denitrifiction and sorption mass (kg/day)'"
          ],
          "rows": 1
        }
      ]
    },
    "timeline": []
  },
  "gwflow_state_obs_conc": {
    "summary": {
      "unit": "out_gwobs_sol",
      "headers": [],
      "index_reads": [],
      "data_reads": [],
      "header_writes": [],
      "data_writes": [
        {
          "columns": [
            "'Daily solute concentration (mg/L) values for observation wells'"
          ],
          "rows": 1
        },
        {
          "columns": [
            "'cell:'",
            "gw_obs_cells(k),k=1,gw_num_obs_wells"
          ],
          "rows": 1
        }
      ]
    },
    "timeline": []
  },
  "gwflow.lsucell": {
    "summary": {
      "unit": "in_lsu_cell",
      "headers": [
        "header",
        "nlsu",
        "nlsu_connected",
        "lsu_id",
        "lsu"
      ],
      "index_reads": [],
      "data_reads": [
        {
          "columns": [
            "lsu",
            "lsu_area",
            "lsu_cells(k,cell_count)",
            "poly_area"
          ],
          "rows": 1
        }
      ],
      "header_writes": [],
      "data_writes": []
    },
    "timeline": []
  },
  "out.key": {
    "summary": {
      "unit": "5100",
      "headers": [],
      "index_reads": [],
      "data_reads": [
        {
          "columns": [
            "dum1",
            "huc12(k)"
          ],
          "rows": 1
        }
      ],
      "header_writes": [],
      "data_writes": []
    },
    "timeline": []
  },
  "in_con%hru_con": {
    "summary": {
      "unit": "5101",
      "headers": [
        "hru_id"
      ],
      "index_reads": [],
      "data_reads": [
        {
          "columns": [
            "dum1",
            "dum2",
            "dum3",
            "dum4",
            "dum5",
            "dum6",
            "dum7",
            "dum8",
            "huc12_id"
          ],
          "rows": 2
        }
      ],
      "header_writes": [],
      "data_writes": []
    },
    "timeline": [
      {
        "kind": "open",
        "raw": "open(5101,file=in_con%hru_con)",
        "line": 1732
      },
      {
        "kind": "read",
        "raw": "read(5101,*)",
        "line": 1736
      },
      {
        "kind": "read",
        "raw": "read(5101,*)",
        "line": 1737
      },
      {
        "kind": "read",
        "raw": "read(5101,*) dum1,dum2,dum3,dum4,dum5,dum6,dum7,dum8,huc12_id",
        "line": 1739
      },
      {
        "kind": "backspace",
        "raw": "backspace(5101)",
        "line": 1740
      },
      {
        "kind": "read",
        "raw": "read(5101,*) hru_id",
        "line": 1744
      },
      {
        "kind": "read",
        "raw": "read(5101,*,end=15) dum1,dum2,dum3,dum4,dum5,dum6,dum7,dum8,huc12_id",
        "line": 1747
      },
      {
        "kind": "backspace",
        "raw": "backspace(5101)",
        "line": 1748
      }
    ]
  },
  "gwflow.hrucell": {
    "summary": {
      "unit": "in_hru_cell",
      "headers": [
        "nhru_connected",
        "hru_id"
      ],
      "index_reads": [],
      "data_reads": [
        {
          "columns": [
            "hru_id",
            "hru_area",
            "hru_cells(k,cell_count)",
            "poly_area"
          ],
          "rows": 1
        }
      ],
      "header_writes": [],
      "data_writes": []
    },
    "timeline": []
  },
  "gwflow.huc12cell": {
    "summary": {
      "unit": "in_huc_cell",
      "headers": [
        "huc12_id"
      ],
      "index_reads": [],
      "data_reads": [
        {
          "columns": [
            "huc12_dum",
            "huc12_connect(k)"
          ],
          "rows": 1
        },
        {
          "columns": [
            "huc12_id",
            "cell_num"
          ],
          "rows": 1
        }
      ],
      "header_writes": [],
      "data_writes": []
    },
    "timeline": []
  },
  "gwflow.cellhru": {
    "summary": {
      "unit": "in_cell_hru",
      "headers": [
        "num_unique",
        "hru_cell",
        "cell_num"
      ],
      "index_reads": [],
      "data_reads": [
        {
          "columns": [
            "cell_num",
            "hru_id",
            "cell_area",
            "poly_area"
          ],
          "rows": 1
        }
      ],
      "header_writes": [],
      "data_writes": []
    },
    "timeline": []
  },
  "gwflow_balance_gw_day": {
    "summary": {
      "unit": "out_gwbal",
      "headers": [],
      "index_reads": [],
      "data_reads": [],
      "header_writes": [],
      "data_writes": [
        {
          "columns": [
            "'Groundwater watershed-wide fluxes for each day'"
          ],
          "rows": 1
        },
        {
          "columns": [
            "'watershed area (m2):'",
            "bsn%area_tot_ha*10000."
          ],
          "rows": 1
        },
        {
          "columns": [
            "'Positive value: groundwater added to aquifer'"
          ],
          "rows": 1
        },
        {
          "columns": [
            "'Negative value: groundwater removed from aquifer'"
          ],
          "rows": 1
        },
        {
          "columns": [
            "'ts:           days time step used for groundwater storage calculations'"
          ],
          "rows": 1
        },
        {
          "columns": [
            "'vbef:         mm   total groundwater volume at the beginning of the day'"
          ],
          "rows": 1
        },
        {
          "columns": [
            "'vaft:         mm   total groundwater volume at the end of the day'"
          ],
          "rows": 1
        },
        {
          "columns": [
            "'rech:         mm   soil water added to groundwater'"
          ],
          "rows": 1
        },
        {
          "columns": [
            "'gwet:         mm   groundwater removed by evapotranspiration'"
          ],
          "rows": 1
        },
        {
          "columns": [
            "'gwsw:         mm   groundwater discharge to streams'"
          ],
          "rows": 1
        },
        {
          "columns": [
            "'swgw:         mm   stream water seepage to groundwater'"
          ],
          "rows": 1
        },
        {
          "columns": [
            "'satx:         mm   saturation excess flow (water table above ground)'"
          ],
          "rows": 1
        },
        {
          "columns": [
            "'soil:         mm   groundwater transferred to HRU soil profile'"
          ],
          "rows": 1
        },
        {
          "columns": [
            "'latl:         mm   groundwater transferred between cells'"
          ],
          "rows": 1
        },
        {
          "columns": [
            "'bndr:         mm   groundwater added/removed at watershed boundary'"
          ],
          "rows": 1
        },
        {
          "columns": [
            "'ppag:         mm   groundwater pumped for irrigation'"
          ],
          "rows": 1
        },
        {
          "columns": [
            "'ppex:         mm   groundwater pumping specified by user'"
          ],
          "rows": 1
        },
        {
          "columns": [
            "'tile:         mm   groundwater removed via tile drains'"
          ],
          "rows": 1
        },
        {
          "columns": [
            "'resv:         mm   groundwater exchanged with reservoirs'"
          ],
          "rows": 1
        },
        {
          "columns": [
            "'wetl:         mm   groundwater outflow to wetlands'"
          ],
          "rows": 1
        },
        {
          "columns": [
            "'canl:         mm   canal seepage to groundwater'"
          ],
          "rows": 1
        },
        {
          "columns": [
            "'fpln:         mm   floodplain exchange'"
          ],
          "rows": 1
        },
        {
          "columns": [
            "'error:        --   water balance error for aquifer'"
          ],
          "rows": 1
        },
        {
          "columns": [
            "'satfr:        --   fraction of cells that have water table at ground'"
          ],
          "rows": 1
        },
        {
          "columns": [
            "'wtdep:        m    average depth to water table for watershed'"
          ],
          "rows": 1
        },
        {
          "columns": [
            "'ppdf:         mm   groundwater demand not satisfied for irrigation'"
          ],
          "rows": 1
        },
        {
          "columns": [
            "gwflow_hdr_day(j),j=1,24"
          ],
          "rows": 1
        }
      ]
    },
    "timeline": []
  },
  "gwflow_balance_gw_yr": {
    "summary": {
      "unit": "out_gwbal_yr",
      "headers": [],
      "index_reads": [],
      "data_reads": [],
      "header_writes": [],
      "data_writes": [
        {
          "columns": [
            "'Groundwater watershed-wide fluxes for each year'"
          ],
          "rows": 1
        },
        {
          "columns": [
            "'watershed area (m2):'",
            "bsn%area_tot_ha*10000."
          ],
          "rows": 1
        },
        {
          "columns": [
            "'Positive value: groundwater added to aquifer'"
          ],
          "rows": 1
        },
        {
          "columns": [
            "'Negative value: groundwater removed from aquifer'"
          ],
          "rows": 1
        },
        {
          "columns": [
            "'dvol:      mm   change in groundwater volume during the year'"
          ],
          "rows": 1
        },
        {
          "columns": [
            "'rech:      mm   soil water added to groundwater'"
          ],
          "rows": 1
        },
        {
          "columns": [
            "'gwet:      mm   groundwater removed by evapotranspiration'"
          ],
          "rows": 1
        },
        {
          "columns": [
            "'gwsw:      mm   groundwater discharge to streams'"
          ],
          "rows": 1
        },
        {
          "columns": [
            "'swgw:      mm   stream water seepage to groundwater'"
          ],
          "rows": 1
        },
        {
          "columns": [
            "'satx:      mm   saturation excess flow (water table above ground)'"
          ],
          "rows": 1
        },
        {
          "columns": [
            "'soil:      mm   groundwater transferred to HRU soil profile'"
          ],
          "rows": 1
        },
        {
          "columns": [
            "'latl:      mm   groundwater transferred between cells'"
          ],
          "rows": 1
        },
        {
          "columns": [
            "'bndr:      mm   groundwater added/removed at watershed boundary'"
          ],
          "rows": 1
        },
        {
          "columns": [
            "'ppag:      mm   groundwater pumped for irrigation'"
          ],
          "rows": 1
        },
        {
          "columns": [
            "'ppex:      mm   groundwater pumping specified by user'"
          ],
          "rows": 1
        },
        {
          "columns": [
            "'tile:      mm   groundwater removed via tile drains'"
          ],
          "rows": 1
        },
        {
          "columns": [
            "'resv:      mm   groundwater exchanged with reservoirs'"
          ],
          "rows": 1
        },
        {
          "columns": [
            "'wetl:      mm   groundwater outflow to wetlands'"
          ],
          "rows": 1
        },
        {
          "columns": [
            "'canl:      mm   canal seepage to groundwater'"
          ],
          "rows": 1
        },
        {
          "columns": [
            "'fpln:      mm   floodplain exchange'"
          ],
          "rows": 1
        },
        {
          "columns": [
            "'ppdf:      mm   groundwater demand not satisfied for irrigation'"
          ],
          "rows": 1
        },
        {
          "columns": [
            "gwflow_hdr_yr(j),j=1,18"
          ],
          "rows": 1
        }
      ]
    },
    "timeline": []
  },
  "gwflow_balance_gw_aa": {
    "summary": {
      "unit": "out_gwbal_aa",
      "headers": [],
      "index_reads": [],
      "data_reads": [],
      "header_writes": [],
      "data_writes": [
        {
          "columns": [
            "'Average annual groundwater watershed-wide fluxes'"
          ],
          "rows": 1
        },
        {
          "columns": [
            "'watershed area (m2):'",
            "bsn%area_tot_ha*10000."
          ],
          "rows": 1
        },
        {
          "columns": [
            "'Positive value: groundwater added to aquifer'"
          ],
          "rows": 1
        },
        {
          "columns": [
            "'Negative value: groundwater removed from aquifer'"
          ],
          "rows": 1
        },
        {
          "columns": [
            "'dvol:      mm   change in groundwater volume during the year'"
          ],
          "rows": 1
        },
        {
          "columns": [
            "'rech:      mm   soil water added to groundwater'"
          ],
          "rows": 1
        },
        {
          "columns": [
            "'gwet:      mm   groundwater removed by evapotranspiration'"
          ],
          "rows": 1
        },
        {
          "columns": [
            "'gwsw:      mm   groundwater discharge to streams'"
          ],
          "rows": 1
        },
        {
          "columns": [
            "'swgw:      mm   stream water seepage to groundwater'"
          ],
          "rows": 1
        },
        {
          "columns": [
            "'satx:      mm   saturation excess flow (water table above ground)'"
          ],
          "rows": 1
        },
        {
          "columns": [
            "'soil:      mm   groundwater transferred to HRU soil profile'"
          ],
          "rows": 1
        },
        {
          "columns": [
            "'latl:      mm   groundwater transferred between cells'"
          ],
          "rows": 1
        },
        {
          "columns": [
            "'bndr:      mm   groundwater added/removed at watershed boundary'"
          ],
          "rows": 1
        },
        {
          "columns": [
            "'ppag:      mm   groundwater pumped for irrigation'"
          ],
          "rows": 1
        },
        {
          "columns": [
            "'ppex:      mm   groundwater pumping specified by user'"
          ],
          "rows": 1
        },
        {
          "columns": [
            "'tile:      mm   groundwater removed via tile drains'"
          ],
          "rows": 1
        },
        {
          "columns": [
            "'resv:      mm   groundwater exchanged with reservoirs'"
          ],
          "rows": 1
        },
        {
          "columns": [
            "'wetl:      mm   groundwater outflow to wetlands'"
          ],
          "rows": 1
        },
        {
          "columns": [
            "'canl:      mm   canal seepage to groundwater'"
          ],
          "rows": 1
        },
        {
          "columns": [
            "'fpln:      mm   floodplain exchange'"
          ],
          "rows": 1
        },
        {
          "columns": [
            "'ppdf:      mm   groundwater demand not satisfied for irrigation'"
          ],
          "rows": 1
        },
        {
          "columns": [
            "gwflow_hdr_aa(j),j=1,18"
          ],
          "rows": 1
        }
      ]
    },
    "timeline": []
  },
  "gwflow_balance_huc12": {
    "summary": {
      "unit": "out_huc12wb",
      "headers": [],
      "index_reads": [],
      "data_reads": [],
      "header_writes": [],
      "data_writes": [
        {
          "columns": [
            "'Total groundwater fluxes for each HUC12'"
          ],
          "rows": 1
        },
        {
          "columns": [
            "'Positive value: groundwater added to aquifer'"
          ],
          "rows": 1
        },
        {
          "columns": [
            "'Negative value: groundwater removed from aquifer'"
          ],
          "rows": 1
        },
        {
          "columns": [
            "'rech:          mm   soil water added to groundwater'"
          ],
          "rows": 1
        },
        {
          "columns": [
            "'gwet:          mm   groundwater removed by evapotranspiration'"
          ],
          "rows": 1
        },
        {
          "columns": [
            "'gwsw:          mm   groundwater discharge to streams'"
          ],
          "rows": 1
        },
        {
          "columns": [
            "'swgw:          mm   stream water seepage to groundwater'"
          ],
          "rows": 1
        },
        {
          "columns": [
            "'satex:         mm   saturation excess flow (water table above ground)'"
          ],
          "rows": 1
        },
        {
          "columns": [
            "'gwsoil:        mm   groundwater transferred to HRU soil profile'"
          ],
          "rows": 1
        },
        {
          "columns": [
            "'lateral:       mm   groundwater added/removed via lateral flow'"
          ],
          "rows": 1
        },
        {
          "columns": [
            "'pump_ag:       mm   groundwater pumped for irrigation'"
          ],
          "rows": 1
        },
        {
          "columns": [
            "'pump_ex:       mm   groundwater pumping specified by user'"
          ],
          "rows": 1
        },
        {
          "columns": [
            "'tile:          mm   groundwater removed via tile drains'"
          ],
          "rows": 1
        },
        {
          "columns": [
            "'res:           mm   groundwater exchanged with reservoirs'"
          ],
          "rows": 1
        },
        {
          "columns": [
            "'wet:           mm   groundwater outflow to wetlands'"
          ],
          "rows": 1
        },
        {
          "columns": [
            "'canal:         mm   canal seepage to groundwater'"
          ],
          "rows": 1
        },
        {
          "columns": [
            "'fplain:        mm   floodplain exchange'"
          ],
          "rows": 1
        },
        {
          "columns": [
            "'pump_def:      mm   groundwater demand not satisfied for irrigation'"
          ],
          "rows": 1
        },
        {
          "columns": [
            "gwflow_hdr_huc12(j),j=1,16"
          ],
          "rows": 1
        }
      ]
    },
    "timeline": []
  },
  "gwflow_balance_huc12_mon": {
    "summary": {
      "unit": "out_huc12wb_mo",
      "headers": [],
      "index_reads": [],
      "data_reads": [],
      "header_writes": [],
      "data_writes": [
        {
          "columns": [
            "'Monthly total groundwater fluxes for each HUC12'"
          ],
          "rows": 1
        },
        {
          "columns": [
            "'Positive value: groundwater added to aquifer'"
          ],
          "rows": 1
        },
        {
          "columns": [
            "'Negative value: groundwater removed from aquifer'"
          ],
          "rows": 1
        },
        {
          "columns": [
            "'rech:          mm   soil water added to groundwater'"
          ],
          "rows": 1
        },
        {
          "columns": [
            "'gwet:          mm   groundwater removed by evapotranspiration'"
          ],
          "rows": 1
        },
        {
          "columns": [
            "'gwsw:          mm   groundwater discharge to streams'"
          ],
          "rows": 1
        },
        {
          "columns": [
            "'swgw:          mm   stream water seepage to groundwater'"
          ],
          "rows": 1
        },
        {
          "columns": [
            "'satex:         mm   saturation excess flow (water table above ground)'"
          ],
          "rows": 1
        },
        {
          "columns": [
            "'gwsoil:        mm   groundwater transferred to HRU soil profile'"
          ],
          "rows": 1
        },
        {
          "columns": [
            "'lateral:       mm   groundwater added/removed via lateral flow'"
          ],
          "rows": 1
        },
        {
          "columns": [
            "'pump_ag:       mm   groundwater pumped for irrigation'"
          ],
          "rows": 1
        },
        {
          "columns": [
            "'pump_ex:       mm   groundwater pumping specified by user'"
          ],
          "rows": 1
        },
        {
          "columns": [
            "'tile:          mm   groundwater removed via tile drains'"
          ],
          "rows": 1
        },
        {
          "columns": [
            "'res:           mm   groundwater exchanged with reservoirs'"
          ],
          "rows": 1
        },
        {
          "columns": [
            "'wet:           mm   groundwater outflow to wetlands'"
          ],
          "rows": 1
        },
        {
          "columns": [
            "'pump_def:      mm   groundwater demand not satisfied for irrigation'"
          ],
          "rows": 1
        },
        {
          "columns": [
            "'canal:         mm   canal seepage to groundwater'"
          ],
          "rows": 1
        },
        {
          "columns": [
            "'fplain:        mm   floodplain exchange'"
          ],
          "rows": 1
        },
        {
          "columns": [
            "gwflow_hdr_huc12_mo(j),j=1,18"
          ],
          "rows": 1
        }
      ]
    },
    "timeline": []
  },
  "file_name": {
    "summary": {
      "unit": "out_solbal_dy+n",
      "headers": [],
      "index_reads": [],
      "data_reads": [],
      "header_writes": [],
      "data_writes": [
        {
          "columns": [
            "'Solute:'",
            "gwsol_nm(n)"
          ],
          "rows": 3
        },
        {
          "columns": [
            "'Groundwater watershed-wide solute loads for each day'"
          ],
          "rows": 1
        },
        {
          "columns": [
            "'Positive value: solute mass added to aquifer'"
          ],
          "rows": 3
        },
        {
          "columns": [
            "'Negative value: solute mass removed from aquifer'"
          ],
          "rows": 3
        },
        {
          "columns": [
            "'ts:        days time step used for groundwater solute calculations'"
          ],
          "rows": 1
        },
        {
          "columns": [
            "'mbef:      kg   total groundwater solute mass at the beginning of the day'"
          ],
          "rows": 1
        },
        {
          "columns": [
            "'maft:      kg   total groundwater solute mass at the end of the day'"
          ],
          "rows": 1
        },
        {
          "columns": [
            "'rech:      kg   solute mass in recharge water'"
          ],
          "rows": 2
        },
        {
          "columns": [
            "'gwsw:      kg   solute mass loaded to streams'"
          ],
          "rows": 2
        },
        {
          "columns": [
            "'swgw:      kg   solute mass loaded from streams'"
          ],
          "rows": 2
        },
        {
          "columns": [
            "'satx:      kg   solute mass loaded to streams by saturation excess flow'"
          ],
          "rows": 2
        },
        {
          "columns": [
            "'soil:      kg   solute mass loaded to HRU soil profiles'"
          ],
          "rows": 2
        },
        {
          "columns": [
            "'advn:      kg   solute mass transported by advection'"
          ],
          "rows": 2
        },
        {
          "columns": [
            "'disp:      kg   solute mass transported by dispersion'"
          ],
          "rows": 2
        },
        {
          "columns": [
            "'rcti:      kg   solute mass produced by kinetic reaction'"
          ],
          "rows": 3
        },
        {
          "columns": [
            "'rcto:      kg   solute mass consumed by kinetic reaction'"
          ],
          "rows": 3
        },
        {
          "columns": [
            "'minl:      kg   solute mass added by mineral dissolution'"
          ],
          "rows": 3
        },
        {
          "columns": [
            "'sorb:      kg   solute mass removed by sorption'"
          ],
          "rows": 1
        },
        {
          "columns": [
            "'ppag:      kg   solute mass removed by groundwater pumping for irrigation'"
          ],
          "rows": 2
        },
        {
          "columns": [
            "'ppex:      kg   solute mass removed by groundwater pumping specified by user'"
          ],
          "rows": 2
        },
        {
          "columns": [
            "'tile:      kg   solute mass removed by tile drains'"
          ],
          "rows": 2
        },
        {
          "columns": [
            "'resv:      kg   solute mass loaded to/from reservoirs'"
          ],
          "rows": 2
        },
        {
          "columns": [
            "'wetl:      kg   solute mass loaded to/from wetlands'"
          ],
          "rows": 2
        },
        {
          "columns": [
            "'canl:      kg   solute mass loaded to groundwater from canal seepage'"
          ],
          "rows": 2
        },
        {
          "columns": [
            "'fpln:      kg   solute mass in floodplain exchange'"
          ],
          "rows": 2
        },
        {
          "columns": [
            "'error:     --   mass balance error for aquifer'"
          ],
          "rows": 1
        },
        {
          "columns": [
            "sol_hdr_day(j),j=1,24"
          ],
          "rows": 1
        },
        {
          "columns": [
            "'Groundwater watershed-wide solute loads for each year'"
          ],
          "rows": 1
        },
        {
          "columns": [
            "'delm:     kg   change in groundwater solute mass during the year'"
          ],
          "rows": 1
        },
        {
          "columns": [
            "'rech:     kg   solute mass in recharge water'"
          ],
          "rows": 1
        },
        {
          "columns": [
            "'gwsw:     kg   solute mass loaded to streams'"
          ],
          "rows": 1
        },
        {
          "columns": [
            "'swgw:     kg   solute mass loaded from streams'"
          ],
          "rows": 1
        },
        {
          "columns": [
            "'satx:     kg   solute mass loaded to streams by saturation excess flow'"
          ],
          "rows": 1
        },
        {
          "columns": [
            "'soil:     kg   solute mass loaded to HRU soil profiles'"
          ],
          "rows": 1
        },
        {
          "columns": [
            "'advn:     kg   solute mass transported by advection'"
          ],
          "rows": 1
        },
        {
          "columns": [
            "'disp:     kg   solute mass transported by dispersion'"
          ],
          "rows": 1
        },
        {
          "columns": [
            "'sorb:     kg   solute mass removed by denitrification'"
          ],
          "rows": 1
        },
        {
          "columns": [
            "'ppag:     kg   solute mass removed by groundwater pumping for irrigation'"
          ],
          "rows": 1
        },
        {
          "columns": [
            "'ppex:     kg   solute mass removed by groundwater pumping specified by user'"
          ],
          "rows": 1
        },
        {
          "columns": [
            "'tile:     kg   solute mass removed by tile drains'"
          ],
          "rows": 1
        },
        {
          "columns": [
            "'resv:     kg   solute mass loaded to/from reservoirs'"
          ],
          "rows": 1
        },
        {
          "columns": [
            "'wetl:     kg   solute mass loaded to/from wetlands'"
          ],
          "rows": 1
        },
        {
          "columns": [
            "'canl:     kg   solute mass loaded to groundwater from canal seepage'"
          ],
          "rows": 1
        },
        {
          "columns": [
            "'fpln:     kg   solute mass in floodplain exchange'"
          ],
          "rows": 1
        },
        {
          "columns": [
            "sol_hdr_yr(j),j=1,20"
          ],
          "rows": 1
        },
        {
          "columns": [
            "'Average annual groundwater watershed-wide solute loads'"
          ],
          "rows": 1
        },
        {
          "columns": [
            "'delm:      kg   total change in groundwater solute mass across all years'"
          ],
          "rows": 1
        },
        {
          "columns": [
            "'sorb:      kg   solute mass removed via sorption'"
          ],
          "rows": 1
        },
        {
          "columns": [
            "sol_hdr_aa(j),j=1,20"
          ],
          "rows": 1
        }
      ]
    },
    "timeline": [
      {
        "kind": "open",
        "raw": "open(out_solbal_dy+n,file=file_name)",
        "line": 2123
      },
      {
        "kind": "write",
        "raw": "write(out_solbal_dy+n,*) 'Solute:',gwsol_nm(n)",
        "line": 2124
      },
      {
        "kind": "write",
        "raw": "write(out_solbal_dy+n,*) 'Groundwater watershed-wide solute loads for each day'",
        "line": 2125
      },
      {
        "kind": "write",
        "raw": "write(out_solbal_dy+n,*)",
        "line": 2126
      },
      {
        "kind": "write",
        "raw": "write(out_solbal_dy+n,*) 'Positive value: solute mass added to aquifer'",
        "line": 2127
      },
      {
        "kind": "write",
        "raw": "write(out_solbal_dy+n,*) 'Negative value: solute mass removed from aquifer'",
        "line": 2128
      },
      {
        "kind": "write",
        "raw": "write(out_solbal_dy+n,*)",
        "line": 2129
      },
      {
        "kind": "write",
        "raw": "write(out_solbal_dy+n,*) 'ts:        days time step used for groundwater solute calculations'",
        "line": 2130
      },
      {
        "kind": "write",
        "raw": "write(out_solbal_dy+n,*) 'mbef:      kg   total groundwater solute mass at the beginning of the day'",
        "line": 2131
      },
      {
        "kind": "write",
        "raw": "write(out_solbal_dy+n,*) 'maft:      kg   total groundwater solute mass at the end of the day'",
        "line": 2132
      },
      {
        "kind": "write",
        "raw": "write(out_solbal_dy+n,*) 'rech:      kg   solute mass in recharge water'",
        "line": 2133
      },
      {
        "kind": "write",
        "raw": "write(out_solbal_dy+n,*) 'gwsw:      kg   solute mass loaded to streams'",
        "line": 2134
      },
      {
        "kind": "write",
        "raw": "write(out_solbal_dy+n,*) 'swgw:      kg   solute mass loaded from streams'",
        "line": 2135
      },
      {
        "kind": "write",
        "raw": "write(out_solbal_dy+n,*) 'satx:      kg   solute mass loaded to streams by saturation excess flow'",
        "line": 2136
      },
      {
        "kind": "write",
        "raw": "write(out_solbal_dy+n,*) 'soil:      kg   solute mass loaded to HRU soil profiles'",
        "line": 2137
      },
      {
        "kind": "write",
        "raw": "write(out_solbal_dy+n,*) 'advn:      kg   solute mass transported by advection'",
        "line": 2138
      },
      {
        "kind": "write",
        "raw": "write(out_solbal_dy+n,*) 'disp:      kg   solute mass transported by dispersion'",
        "line": 2139
      },
      {
        "kind": "write",
        "raw": "write(out_solbal_dy+n,*) 'rcti:      kg   solute mass produced by kinetic reaction'",
        "line": 2140
      },
      {
        "kind": "write",
        "raw": "write(out_solbal_dy+n,*) 'rcto:      kg   solute mass consumed by kinetic reaction'",
        "line": 2141
      },
      {
        "kind": "write",
        "raw": "write(out_solbal_dy+n,*) 'minl:      kg   solute mass added by mineral dissolution'",
        "line": 2142
      },
      {
        "kind": "write",
        "raw": "write(out_solbal_dy+n,*) 'sorb:      kg   solute mass removed by sorption'",
        "line": 2143
      },
      {
        "kind": "write",
        "raw": "write(out_solbal_dy+n,*) 'ppag:      kg   solute mass removed by groundwater pumping for irrigation'",
        "line": 2144
      },
      {
        "kind": "write",
        "raw": "write(out_solbal_dy+n,*) 'ppex:      kg   solute mass removed by groundwater pumping specified by user'",
        "line": 2145
      },
      {
        "kind": "write",
        "raw": "write(out_solbal_dy+n,*) 'tile:      kg   solute mass removed by tile drains'",
        "line": 2146
      },
      {
        "kind": "write",
        "raw": "write(out_solbal_dy+n,*) 'resv:      kg   solute mass loaded to/from reservoirs'",
        "line": 2147
      },
      {
        "kind": "write",
        "raw": "write(out_solbal_dy+n,*) 'wetl:      kg   solute mass loaded to/from wetlands'",
        "line": 2148
      },
      {
        "kind": "write",
        "raw": "write(out_solbal_dy+n,*) 'canl:      kg   solute mass loaded to groundwater from canal seepage'",
        "line": 2149
      },
      {
        "kind": "write",
        "raw": "write(out_solbal_dy+n,*) 'fpln:      kg   solute mass in floodplain exchange'",
        "line": 2150
      },
      {
        "kind": "write",
        "raw": "write(out_solbal_dy+n,*) 'error:     --   mass balance error for aquifer'",
        "line": 2151
      },
      {
        "kind": "write",
        "raw": "write(out_solbal_dy+n,*)",
        "line": 2152
      },
      {
        "kind": "write",
        "raw": "write(out_solbal_dy+n,119) (sol_hdr_day(j),j=1,24)",
        "line": 2155
      },
      {
        "kind": "open",
        "raw": "open(out_solbal_yr+n,file=file_name)",
        "line": 2161
      },
      {
        "kind": "write",
        "raw": "write(out_solbal_yr+n,*) 'Solute:',gwsol_nm(n)",
        "line": 2162
      },
      {
        "kind": "write",
        "raw": "write(out_solbal_yr+n,*) 'Groundwater watershed-wide solute loads for each year'",
        "line": 2163
      },
      {
        "kind": "write",
        "raw": "write(out_solbal_yr+n,*)",
        "line": 2164
      },
      {
        "kind": "write",
        "raw": "write(out_solbal_yr+n,*) 'Positive value: solute mass added to aquifer'",
        "line": 2165
      },
      {
        "kind": "write",
        "raw": "write(out_solbal_yr+n,*) 'Negative value: solute mass removed from aquifer'",
        "line": 2166
      },
      {
        "kind": "write",
        "raw": "write(out_solbal_yr+n,*)",
        "line": 2167
      },
      {
        "kind": "write",
        "raw": "write(out_solbal_yr+n,*) 'delm:     kg   change in groundwater solute mass during the year'",
        "line": 2168
      },
      {
        "kind": "write",
        "raw": "write(out_solbal_yr+n,*) 'rech:     kg   solute mass in recharge water'",
        "line": 2169
      },
      {
        "kind": "write",
        "raw": "write(out_solbal_yr+n,*) 'gwsw:     kg   solute mass loaded to streams'",
        "line": 2170
      },
      {
        "kind": "write",
        "raw": "write(out_solbal_yr+n,*) 'swgw:     kg   solute mass loaded from streams'",
        "line": 2171
      },
      {
        "kind": "write",
        "raw": "write(out_solbal_yr+n,*) 'satx:     kg   solute mass loaded to streams by saturation excess flow'",
        "line": 2172
      },
      {
        "kind": "write",
        "raw": "write(out_solbal_yr+n,*) 'soil:     kg   solute mass loaded to HRU soil profiles'",
        "line": 2173
      },
      {
        "kind": "write",
        "raw": "write(out_solbal_yr+n,*) 'advn:     kg   solute mass transported by advection'",
        "line": 2174
      },
      {
        "kind": "write",
        "raw": "write(out_solbal_yr+n,*) 'disp:     kg   solute mass transported by dispersion'",
        "line": 2175
      },
      {
        "kind": "write",
        "raw": "write(out_solbal_yr+n,*) 'rcti:      kg   solute mass produced by kinetic reaction'",
        "line": 2176
      },
      {
        "kind": "write",
        "raw": "write(out_solbal_yr+n,*) 'rcto:      kg   solute mass consumed by kinetic reaction'",
        "line": 2177
      },
      {
        "kind": "write",
        "raw": "write(out_solbal_yr+n,*) 'minl:      kg   solute mass added by mineral dissolution'",
        "line": 2178
      },
      {
        "kind": "write",
        "raw": "write(out_solbal_yr+n,*) 'sorb:     kg   solute mass removed by denitrification'",
        "line": 2179
      },
      {
        "kind": "write",
        "raw": "write(out_solbal_yr+n,*) 'ppag:     kg   solute mass removed by groundwater pumping for irrigation'",
        "line": 2180
      },
      {
        "kind": "write",
        "raw": "write(out_solbal_yr+n,*) 'ppex:     kg   solute mass removed by groundwater pumping specified by user'",
        "line": 2181
      },
      {
        "kind": "write",
        "raw": "write(out_solbal_yr+n,*) 'tile:     kg   solute mass removed by tile drains'",
        "line": 2182
      },
      {
        "kind": "write",
        "raw": "write(out_solbal_yr+n,*) 'resv:     kg   solute mass loaded to/from reservoirs'",
        "line": 2183
      },
      {
        "kind": "write",
        "raw": "write(out_solbal_yr+n,*) 'wetl:     kg   solute mass loaded to/from wetlands'",
        "line": 2184
      },
      {
        "kind": "write",
        "raw": "write(out_solbal_yr+n,*) 'canl:     kg   solute mass loaded to groundwater from canal seepage'",
        "line": 2185
      },
      {
        "kind": "write",
        "raw": "write(out_solbal_yr+n,*) 'fpln:     kg   solute mass in floodplain exchange'",
        "line": 2186
      },
      {
        "kind": "write",
        "raw": "write(out_solbal_yr+n,*)",
        "line": 2187
      },
      {
        "kind": "write",
        "raw": "write(out_solbal_yr+n,120) (sol_hdr_yr(j),j=1,20)",
        "line": 2190
      },
      {
        "kind": "open",
        "raw": "open(out_solbal_aa+n,file=file_name)",
        "line": 2216
      },
      {
        "kind": "write",
        "raw": "write(out_solbal_aa+n,*) 'Solute:',gwsol_nm(n)",
        "line": 2217
      },
      {
        "kind": "write",
        "raw": "write(out_solbal_aa+n,*) 'Average annual groundwater watershed-wide solute loads'",
        "line": 2218
      },
      {
        "kind": "write",
        "raw": "write(out_solbal_aa+n,*)",
        "line": 2219
      },
      {
        "kind": "write",
        "raw": "write(out_solbal_aa+n,*) 'Positive value: solute mass added to aquifer'",
        "line": 2220
      },
      {
        "kind": "write",
        "raw": "write(out_solbal_aa+n,*) 'Negative value: solute mass removed from aquifer'",
        "line": 2221
      },
      {
        "kind": "write",
        "raw": "write(out_solbal_aa+n,*)",
        "line": 2222
      },
      {
        "kind": "write",
        "raw": "write(out_solbal_aa+n,*) 'delm:      kg   total change in groundwater solute mass across all years'",
        "line": 2223
      },
      {
        "kind": "write",
        "raw": "write(out_solbal_aa+n,*) 'rech:      kg   solute mass in recharge water'",
        "line": 2224
      },
      {
        "kind": "write",
        "raw": "write(out_solbal_aa+n,*) 'gwsw:      kg   solute mass loaded to streams'",
        "line": 2225
      },
      {
        "kind": "write",
        "raw": "write(out_solbal_aa+n,*) 'swgw:      kg   solute mass loaded from streams'",
        "line": 2226
      },
      {
        "kind": "write",
        "raw": "write(out_solbal_aa+n,*) 'satx:      kg   solute mass loaded to streams by saturation excess flow'",
        "line": 2227
      },
      {
        "kind": "write",
        "raw": "write(out_solbal_aa+n,*) 'soil:      kg   solute mass loaded to HRU soil profiles'",
        "line": 2228
      },
      {
        "kind": "write",
        "raw": "write(out_solbal_aa+n,*) 'advn:      kg   solute mass transported by advection'",
        "line": 2229
      },
      {
        "kind": "write",
        "raw": "write(out_solbal_aa+n,*) 'disp:      kg   solute mass transported by dispersion'",
        "line": 2230
      },
      {
        "kind": "write",
        "raw": "write(out_solbal_aa+n,*) 'rcti:      kg   solute mass produced by kinetic reaction'",
        "line": 2231
      },
      {
        "kind": "write",
        "raw": "write(out_solbal_aa+n,*) 'rcto:      kg   solute mass consumed by kinetic reaction'",
        "line": 2232
      },
      {
        "kind": "write",
        "raw": "write(out_solbal_aa+n,*) 'minl:      kg   solute mass added by mineral dissolution'",
        "line": 2233
      },
      {
        "kind": "write",
        "raw": "write(out_solbal_aa+n,*) 'sorb:      kg   solute mass removed via sorption'",
        "line": 2234
      },
      {
        "kind": "write",
        "raw": "write(out_solbal_aa+n,*) 'ppag:      kg   solute mass removed by groundwater pumping for irrigation'",
        "line": 2235
      },
      {
        "kind": "write",
        "raw": "write(out_solbal_aa+n,*) 'ppex:      kg   solute mass removed by groundwater pumping specified by user'",
        "line": 2236
      },
      {
        "kind": "write",
        "raw": "write(out_solbal_aa+n,*) 'tile:      kg   solute mass removed by tile drains'",
        "line": 2237
      },
      {
        "kind": "write",
        "raw": "write(out_solbal_aa+n,*) 'resv:      kg   solute mass loaded to/from reservoirs'",
        "line": 2238
      },
      {
        "kind": "write",
        "raw": "write(out_solbal_aa+n,*) 'wetl:      kg   solute mass loaded to/from wetlands'",
        "line": 2239
      },
      {
        "kind": "write",
        "raw": "write(out_solbal_aa+n,*) 'canl:      kg   solute mass loaded to groundwater from canal seepage'",
        "line": 2240
      },
      {
        "kind": "write",
        "raw": "write(out_solbal_aa+n,*) 'fpln:      kg   solute mass in floodplain exchange'",
        "line": 2241
      },
      {
        "kind": "write",
        "raw": "write(out_solbal_aa+n,*)",
        "line": 2242
      },
      {
        "kind": "write",
        "raw": "write(out_solbal_aa+n,120) (sol_hdr_aa(j),j=1,20)",
        "line": 2245
      }
    ]
  },
  "gwflow_state_head": {
    "summary": {
      "unit": "out_gwheads",
      "headers": [],
      "index_reads": [],
      "data_reads": [],
      "header_writes": [],
      "data_writes": [
        {
          "columns": [
            "'Initial head values (m)'"
          ],
          "rows": 1
        },
        {
          "columns": [
            "grid_val(i,j),j=1,grid_ncol"
          ],
          "rows": 1
        },
        {
          "columns": [
            "gw_state(i)%head,i=1,ncell"
          ],
          "rows": 1
        }
      ]
    },
    "timeline": []
  },
  "gwflow_state_conc": {
    "summary": {
      "unit": "out_gwconc",
      "headers": [],
      "index_reads": [],
      "data_reads": [],
      "header_writes": [],
      "data_writes": [
        {
          "columns": [
            "'Initial concentration values (mg/L)'"
          ],
          "rows": 1
        },
        {
          "columns": [
            "'solute:'",
            "gwsol_nm(s)"
          ],
          "rows": 1
        },
        {
          "columns": [
            "grid_val(i,j),j=1,grid_ncol"
          ],
          "rows": 1
        },
        {
          "columns": [
            "gwsol_state(i)%solute(s)%conc,i=1,ncell"
          ],
          "rows": 1
        }
      ]
    },
    "timeline": []
  },
  "gwflow_state_head_mo": {
    "summary": {
      "unit": "out_head_mo",
      "headers": [],
      "index_reads": [],
      "data_reads": [],
      "header_writes": [],
      "data_writes": [
        {
          "columns": [
            "'Monthly average groundwater head (m) for each grid cell'"
          ],
          "rows": 1
        }
      ]
    },
    "timeline": []
  },
  "gwflow_state_head_yr": {
    "summary": {
      "unit": "out_head_yr",
      "headers": [],
      "index_reads": [],
      "data_reads": [],
      "header_writes": [],
      "data_writes": [
        {
          "columns": [
            "'Annual average groundwater head (m) for each grid cell'"
          ],
          "rows": 1
        }
      ]
    },
    "timeline": []
  },
  "gwflow_state_conc_mo": {
    "summary": {
      "unit": "out_conc_mo",
      "headers": [],
      "index_reads": [],
      "data_reads": [],
      "header_writes": [],
      "data_writes": [
        {
          "columns": [
            "'Monthly average solute concentration (g/m3) for each grid cell'"
          ],
          "rows": 1
        }
      ]
    },
    "timeline": []
  },
  "gwflow_state_conc_yr": {
    "summary": {
      "unit": "out_conc_yr",
      "headers": [],
      "index_reads": [],
      "data_reads": [],
      "header_writes": [],
      "data_writes": [
        {
          "columns": [
            "'Annual average solute concentration (g/m3) for each grid cell'"
          ],
          "rows": 1
        }
      ]
    },
    "timeline": []
  },
  "gwflow.streamobs": {
    "summary": {
      "unit": "in_str_obs",
      "headers": [
        "gw_num_obs_chan",
        "gw_flow_cal",
        "gw_flow_cal_yrs"
      ],
      "index_reads": [],
      "data_reads": [
        {
          "columns": [
            "obs_channels(i)"
          ],
          "rows": 1
        },
        {
          "columns": [
            "obs_flow_vals(j,i),j=1,gw_num_obs_chan"
          ],
          "rows": 1
        }
      ],
      "header_writes": [],
      "data_writes": []
    },
    "timeline": []
  },
  "gwflow_state_obs_flow": {
    "summary": {
      "unit": "out_strobs",
      "headers": [],
      "index_reads": [],
      "data_reads": [],
      "header_writes": [],
      "data_writes": [
        {
          "columns": [
            "'Channels: observed vs. simulated monthly values'"
          ],
          "rows": 1
        }
      ]
    },
    "timeline": []
  },
  "gwflow_state_hydsep": {
    "summary": {
      "unit": "out_hyd_sep",
      "headers": [],
      "index_reads": [],
      "data_reads": [],
      "header_writes": [],
      "data_writes": [
        {
          "columns": [
            "'Hydrograph Separation (m3/sec) for each channel'"
          ],
          "rows": 1
        },
        {
          "columns": [
            "'chan_surf:     channel flow contributed from surface runoff'"
          ],
          "rows": 1
        },
        {
          "columns": [
            "'chan_lat:      channel flow contributed from soil lateral flow'"
          ],
          "rows": 1
        },
        {
          "columns": [
            "'chan_gwsw:     channel flow contributed from groundwater discharge'"
          ],
          "rows": 1
        },
        {
          "columns": [
            "'chan_swgw:     channel flow seeped from channel to aquifer'"
          ],
          "rows": 1
        },
        {
          "columns": [
            "'chan_satexgw:  channel flow contributed from groundwater saturation excess'"
          ],
          "rows": 1
        },
        {
          "columns": [
            "'chan_satexsw:  channel flow contributed from saturation excess runoff'"
          ],
          "rows": 1
        },
        {
          "columns": [
            "'chan_tile:     channel flow contributed from tile drain flow'"
          ],
          "rows": 1
        },
        {
          "columns": [
            "hydsep_hdr(j),j=1,10"
          ],
          "rows": 1
        }
      ]
    },
    "timeline": []
  },
  "line_number": 9
}