{
  "file": "smp_grass_wway.f90",
  "line_number": 1,
  "calls": [
    {
      "name": "surfq",
      "line_number": 72
    },
    {
      "name": "hru",
      "line_number": 76
    },
    {
      "name": "tc_gwat",
      "line_number": 78
    },
    {
      "name": "grwway_vel",
      "line_number": 81
    },
    {
      "name": "qman",
      "line_number": 96
    },
    {
      "name": "sedyld",
      "line_number": 101
    },
    {
      "name": "sedminpa",
      "line_number": 177
    },
    {
      "name": "sedminps",
      "line_number": 178
    },
    {
      "name": "sedorgp",
      "line_number": 179
    },
    {
      "name": "surqsolp",
      "line_number": 180
    },
    {
      "name": "sedorgn",
      "line_number": 181
    },
    {
      "name": "surqno3",
      "line_number": 182
    },
    {
      "name": "lagyld",
      "line_number": 185
    },
    {
      "name": "sanyld",
      "line_number": 190
    },
    {
      "name": "sagyld",
      "line_number": 195
    },
    {
      "name": "silyld",
      "line_number": 200
    },
    {
      "name": "clayld",
      "line_number": 205
    },
    {
      "name": "pest",
      "line_number": 224
    }
  ]
}